airflow/providers/hashicorp/__init__.py
airflow/providers/hashicorp/get_provider_info.py
airflow/providers/hashicorp/version_compat.py
airflow/providers/hashicorp/_internal_client/__init__.py
airflow/providers/hashicorp/_internal_client/vault_client.py
airflow/providers/hashicorp/hooks/__init__.py
airflow/providers/hashicorp/hooks/vault.py
airflow/providers/hashicorp/secrets/__init__.py
airflow/providers/hashicorp/secrets/vault.py
apache_airflow_providers_hashicorp-4.4.2.dist-info/entry_points.txt
apache_airflow_providers_hashicorp-4.4.2.dist-info/licenses/LICENSE
apache_airflow_providers_hashicorp-4.4.2.dist-info/licenses/NOTICE
apache_airflow_providers_hashicorp-4.4.2.dist-info/WHEEL
apache_airflow_providers_hashicorp-4.4.2.dist-info/METADATA
apache_airflow_providers_hashicorp-4.4.2.dist-info/RECORD
